byfintech/__init__.py
byfintech-0.0.0.dist-info/LICENSE
byfintech-0.0.0.dist-info/METADATA
byfintech-0.0.0.dist-info/WHEEL
byfintech-0.0.0.dist-info/top_level.txt
byfintech-0.0.0.dist-info/RECORD
