Metadata-Version: 2.1
Name: byfintech
Version: 0.0.0
Summary: byfintech
Home-page: https://github.com/BruceYanghy/ByFinTech
Author: Hongyang Yang
Author-email: hy2500@columbia.edu
License: MIT
Keywords: Reinforcment Learning
Classifier: License :: OSI Approved :: MIT License
Classifier: Programming Language :: Python
Classifier: Programming Language :: Python :: 3
Classifier: Programming Language :: Python :: 3.8
Classifier: Programming Language :: Python :: 3.9
Classifier: Programming Language :: Python :: 3.10
Classifier: Programming Language :: Python :: Implementation :: CPython
Classifier: Programming Language :: Python :: Implementation :: PyPy
Requires-Python: >=3.8
License-File: LICENSE
